iplotProcessing/__init__.py
iplotProcessing/_version.py
iplotProcessing/common/__init__.py
iplotProcessing/common/errors.py
iplotProcessing/common/grid_mixing.py
iplotProcessing/common/interpolation.py
iplotProcessing/common/units.py
iplotProcessing/core/__init__.py
iplotProcessing/core/bobject.py
iplotProcessing/core/signal.py
iplotProcessing/math/__init__.py
iplotProcessing/math/compute/__init__.py
iplotProcessing/math/compute/correlation.py
iplotProcessing/math/compute/fft.py
iplotProcessing/math/compute/interpolation.py
iplotProcessing/math/compute/zero_crossings.py
iplotProcessing/math/expressions/__init__.py
iplotProcessing/math/expressions/augmented.py
iplotProcessing/math/expressions/binary.py
iplotProcessing/math/expressions/reflected.py
iplotProcessing/math/expressions/unary.py
iplotProcessing/math/pre_processing/__init__.py
iplotProcessing/math/pre_processing/binning.py
iplotProcessing/math/pre_processing/grid_mixing.py
iplotProcessing/math/pre_processing/sampling.py
iplotProcessing/math/pre_processing/smoothing.py
iplotProcessing/tests/__init__.py
iplotProcessing/tests/test_01_expression_parsing.py
iplotProcessing/tests/test_02_bobject_0d_buffer.py
iplotProcessing/tests/test_03_bobject_1d_buffer.py
iplotProcessing/tests/test_04_bobject_2d_buffer.py
iplotProcessing/tests/test_05_buffer_object_ufunc.py
iplotProcessing/tests/test_06_signal_ufunc.py
iplotProcessing/tests/test_07_grid_mixin_union.py
iplotProcessing/tests/test_08_grid_mixin_intersection.py
iplotProcessing/tests/test_09_time_resolution.py
iplotProcessing/tests/test_10_signal_1d_add.py
iplotProcessing/tests/test_11_signal_2d_add.py
iplotProcessing/tests/test_12_signal_binary_ops.py
iplotProcessing/tools/__init__.py
iplotProcessing/tools/default_modules.json
iplotProcessing/tools/hasher.py
iplotProcessing/tools/parsers.py
iplotprocessing-1.1.5.post1.dist-info/METADATA
iplotprocessing-1.1.5.post1.dist-info/WHEEL
iplotprocessing-1.1.5.post1.dist-info/top_level.txt
iplotprocessing-1.1.5.post1.dist-info/RECORD
