Metadata-Version: 2.4
Name: iplotProcessing
Version: 1.1.5.post1
Summary: Data processing for applications using IDSs or CBS
Author-email: ITER Organization <jscabanilla@minsait.com>
Maintainer-email: Jhon Steeven Cabanilla Alvarado <jscabanilla@minsait.com>, Pablo Martin Villares <pmartin@minsait.com>, Mario Gomez Ballesteros <mgomezb@minsait.com>
License: MIT
Project-URL: Homepage, https://github.com/iplot-viz/iplotprocessing
Project-URL: Repository, https://github.com/iplot-viz/iplotprocessing.git
Project-URL: Issues, https://github.com/iplot-viz/iplotprocessing/issues
Keywords: Data,Processing,Preprocessing,IMAS,CODAC
Classifier: Programming Language :: Python :: 3
Classifier: License :: OSI Approved :: MIT License
Classifier: Operating System :: OS Independent
Requires-Python: >=3.9
Requires-Dist: iplotLogging>=1.2.0
Requires-Dist: numpy>=1.19.5
Requires-Dist: scipy>=1.5.4
Provides-Extra: test
Requires-Dist: pytest>=6.0; extra == "test"
